{
  "ads": [
    {
      "name": "NICOLE",
      "phone": "+35699033418",
      "whatsapp": true,
      "age": 25,
      "nationality": "Non spécifié",
      "description": "Bonjour bébé, je visite cette merveilleuse ville pour la première fois et je ne resterai que quelques semaines. Je m'assurerai que chaque rencontre soit mémorable du début à la fin, alors ne manquez pas l'occasion de me rencontrer!",
      "services": ["Position 69", "Sexe anal", "Fellation avec/sans préservatif", "Expérience petite amie", "Sexe lesbien", "Massage érotique", "Gorge profonde", "Dirty talk", "Kamasutra", "Lingerie", "Expérience pornstar", "Anulingus", "Jouets/Godes", "Services pour couples", "Fétichisme des pieds", "Douche dorée", "Maîtresse", "Squirting", "Massage de la prostate"],
      "meetingPlaces": ["Incall", "Outcall"],
      "workingHours": "24/7",
      "gender": "female",
      "location": "Msida",
      "country": "MT",
      "price": 130,
      "height": 156,
      "weight": 58,
      "cupSize": "B"
    },
    {
      "name": "KATHERYN",
      "phone": "+35699741303",
      "whatsapp": true,
      "age": 28,
      "nationality": "Vénézuélienne",
      "description": "Belle Trans, Katherine nouveau top model, je suis une jeune princesse vénézuélienne, super féminine, magnifique et très sexy. Corps incroyable, avec des courbes.",
      "services": ["Position 69", "Sexe anal", "Fellation avec préservatif", "Massage érotique", "Massage de la prostate", "Massage tantrique", "Massage anal", "Léchage et succion de boules", "Gorge profonde", "Dirty talk", "Fisting", "Kamasutra", "Lingerie", "Rasage intime", "Jouets/Godes", "Pour couples", "BDSM", "Fétichisme", "Maîtresse", "Squirting"],
      "meetingPlaces": ["Incall", "Outcall"],
      "workingHours": "24/7",
      "gender": "transsexual",
      "location": "Msida",
      "country": "MT",
      "price": 150,
      "height": 175,
      "weight": 70,
      "cupSize": "F"
    },
    {
      "name": "BIANKA",
      "phone": "+35699656662",
      "whatsapp": true,
      "age": 24,
      "nationality": "Non spécifié",
      "description": "Je suis une jeune brune avec un corps chaud. J'ai le meilleur service en style GFE... prête à plaire. Laissez-moi vous emmener au paradis. Je suis une nouvelle fille indépendante.",
      "services": ["Position 69", "Sexe anal", "Fellation avec/sans préservatif", "Expérience petite amie", "Massage érotique", "Massage de la prostate", "Dirty talk", "Kamasutra", "Lingerie", "Expérience pornstar", "Anulingus", "Services pour couples", "Fétichisme des pieds", "Douche dorée", "Maîtresse", "Squirting"],
      "meetingPlaces": ["Incall"],
      "workingHours": "24/7",
      "gender": "female",
      "location": "Msida",
      "country": "MT",
      "price": 130,
      "height": 160,
      "weight": 52,
      "cupSize": "B"
    },
    {
      "name": "Isabella",
      "phone": "+35699561222",
      "whatsapp": true,
      "age": 27,
      "nationality": "Non spécifié",
      "description": "Je suis une fille charmante, sensuelle, aimante et discrète prête à vous faire passer un bon moment",
      "services": ["Massage érotique", "Expérience petite amie", "Gorge profonde", "Lingerie", "Jouets/Godes", "Bondage", "Fétichisme", "Fétichisme des pieds"],
      "meetingPlaces": ["Incall", "Outcall"],
      "workingHours": "24/7",
      "gender": "female",
      "location": "Msida",
      "country": "MT",
      "price": 100,
      "height": 57,
      "weight": 60,
      "cupSize": "B"
    },
    {
      "name": "Sofía",
      "phone": "+35677278126",
      "whatsapp": true,
      "age": 20,
      "nationality": "Non spécifié",
      "description": "Une femme d'une beauté captivante et d'une présence magnétique qui aime la conversation et créer des expériences spéciales, intimes et mémorables. Sophistiquée, attentive et passionnée.",
      "services": ["Position 69", "Fellation avec préservatif", "Expérience petite amie", "Kamasutra"],
      "meetingPlaces": ["Incall", "Outcall"],
      "workingHours": "24/7",
      "gender": "female",
      "location": "Msida",
      "country": "MT",
      "price": 60,
      "height": 170,
      "weight": 50,
      "cupSize": "D"
    },
    {
      "name": "KATY",
      "phone": "+35699976128",
      "whatsapp": true,
      "age": 25,
      "nationality": "Colombienne",
      "description": "Je suis une femme colombienne sexy et belle, pleine de désir. J'ai 25 ans et j'adore faire des fellations en gorge profonde incroyables et vous rendre incroyablement excité et prêt à me chevaucher.",
      "services": ["Fellation avec/sans préservatif", "Gorge profonde", "Expérience petite amie", "Sexe anal", "Massage érotique", "BDSM", "Bondage", "Services fétichistes"],
      "meetingPlaces": ["Incall", "Outcall"],
      "workingHours": "24/7",
      "gender": "female",
      "location": "Msida",
      "country": "MT",
      "price": 150,
      "height": 169,
      "weight": 50,
      "cupSize": "D"
    },
    {
      "name": "Kim",
      "phone": "+35679580133",
      "whatsapp": true,
      "age": 28,
      "nationality": "Colombienne",
      "description": "Disponible MAINTENANT pour une durée limitée. Ne manquez pas la bombe transsexuelle blonde colombienne la plus sexy. Apparence superbe, corps mince avec seins fermes 40B et fesses toniques.",
      "services": ["Services Incall", "Séances virtuelles", "Plans à trois", "Arrangements pour couples"],
      "meetingPlaces": ["Incall"],
      "workingHours": "24/7",
      "gender": "transsexual",
      "location": "Msida",
      "country": "MT",
      "price": 200,
      "height": 171,
      "weight": 70,
      "cupSize": "B"
    },
    {
      "name": "Valeria",
      "phone": "+35699648006",
      "whatsapp": true,
      "age": 31,
      "nationality": "Non spécifié",
      "description": "Bonjour Gentleman! Mon nom est Sofia. Je suis une escorte très sensuelle qui aime s'amuser et profiter de la vie. Si vous cherchez un bon moment de détente, d'oubli et de jovialité, mes bras sont prêts à vous accueillir.",
      "services": ["Position 69", "Sexe anal", "Fellation avec préservatif", "Massage érotique", "Massage de la prostate", "Massage anal", "Facesitting", "Kamasutra", "Lingerie", "Photo/Vidéo", "Fétichisme", "Squirting"],
      "meetingPlaces": ["Outcall"],
      "workingHours": "24/7",
      "gender": "female",
      "location": "Msida",
      "country": "MT",
      "price": 200,
      "height": 160,
      "weight": 60,
      "cupSize": "A"
    },
    {
      "name": "IRMA IRMA",
      "phone": "+35699688500",
      "whatsapp": true,
      "age": 22,
      "nationality": "Non spécifié",
      "description": "DERNIÈRE SEMAINE À MALTE!! VENEZ ME GOÛTER BÉBÉ JOURS LIMITÉS!!!!!",
      "services": ["Fellation avec préservatif", "Fellation sans préservatif", "Expérience petite amie"],
      "meetingPlaces": ["Incall", "Outcall"],
      "workingHours": "24/7",
      "gender": "female",
      "location": "Msida",
      "country": "MT",
      "price": 120,
      "height": 166,
      "weight": 66,
      "cupSize": "C"
    },
    {
      "name": "Mix sandra",
      "phone": "+35699723740",
      "whatsapp": true,
      "age": 22,
      "nationality": "Non spécifié",
      "description": "Je suis une fille noire chocolat avec la bonne source et très propre et chaude. Je fais de bonnes fellations et du sexe, active et passive. Un essai vous convaincra. Je propose également des massages avec fin heureuse.",
      "services": ["Position 69", "Sexe anal", "Sexe anal sans préservatif", "Fellation sans préservatif", "Expérience petite amie", "Gorge profonde", "Dirty talk", "Fisting", "Gang bang", "Lingerie", "Sexe en plein air", "Expérience pornstar", "Photo/Vidéo", "Jouets/Godes", "Massage tantrique", "Massage mousse", "BDSM", "Sexe clinique", "Fétichisme", "Fétichisme des pieds", "Douche dorée", "Cuir/Latex/PVC", "Maîtresse", "Fessée"],
      "meetingPlaces": ["Incall"],
      "workingHours": "24/7",
      "gender": "transsexual",
      "location": "Msida",
      "country": "MT",
      "price": 150,
      "height": 176,
      "weight": 60,
      "cupSize": "A"
    },
    {
      "name": "Catalina",
      "phone": "+35699068760",
      "whatsapp": true,
      "age": 25,
      "nationality": "Non spécifié",
      "description": "Catalina est disponible pour vous offrir une expérience inoubliable.",
      "services": ["Position 69", "Fellation avec préservatif", "Fellation sans préservatif", "Massage érotique", "Massage de la prostate", "Gorge profonde", "Lingerie", "Sexe en plein air", "Expérience pornstar", "Jouets/Godes", "Pour couples"],
      "meetingPlaces": ["Incall"],
      "workingHours": "24/7",
      "gender": "female",
      "location": "Msida",
      "country": "MT",
      "price": 150,
      "height": 160,
      "weight": 61,
      "cupSize": "B"
    },
    {
      "name": "NIKKIE",
      "phone": "+35677289106",
      "whatsapp": true,
      "age": 26,
      "nationality": "Non spécifié",
      "description": "GFE signifie intimité, physique et émotionnelle. Beaucoup de baisers bien sûr. Des baisers avec la langue partout sur le corps.",
      "services": ["Position 69", "Sexe anal", "Fellation avec/sans préservatif", "Expérience petite amie", "Massage érotique", "Gorge profonde", "Fisting", "Gang bang", "BDSM", "Bondage", "Maîtresse", "Fessée"],
      "meetingPlaces": ["Incall", "Outcall"],
      "workingHours": "24/7",
      "gender": "transsexual",
      "location": "Msida",
      "country": "MT",
      "price": 150,
      "height": 178,
      "weight": 68,
      "cupSize": "F"
    },
    {
      "name": "Melissa",
      "phone": "+35679611503",
      "whatsapp": true,
      "age": 32,
      "nationality": "Latine",
      "description": "Toutes mes photos sont 100% réelles. Elle se décrit comme quelqu'un qui prend soin de son apparence, aime fournir de la compagnie et positionne son travail comme rendant les clients heureux.",
      "services": ["Expérience petite amie", "Accompagnement"],
      "meetingPlaces": ["Incall", "Outcall"],
      "workingHours": "24/7",
      "gender": "female",
      "location": "Msida",
      "country": "MT",
      "price": 120,
      "height": 155,
      "weight": 55,
      "cupSize": "D"
    },
    {
      "name": "Vale",
      "phone": "+35699971576",
      "whatsapp": true,
      "age": 21,
      "nationality": "Non spécifié",
      "description": "Bonjour! Je suis Vale, une fille sexy. J'aime les hommes et les caresses chaudes. Je vous assure que vous ne m'oublierez pas ainsi que notre nuit torride!",
      "services": ["Position 69", "Fellation avec préservatif", "Expérience petite amie", "BDSM", "Bondage", "Sexe clinique", "Fétichisme des pieds", "Douche dorée", "Cuir/Latex/PVC", "Maîtresse", "Fessée", "Gode ceinture", "Squirting", "SCAT"],
      "meetingPlaces": ["Incall", "Outcall"],
      "workingHours": "24/7",
      "gender": "female",
      "location": "Msida",
      "country": "MT",
      "price": 60,
      "height": 160,
      "weight": 45,
      "cupSize": "B"
    },
    {
      "name": "Catalina",
      "phone": "+35699679422",
      "whatsapp": true,
      "age": 20,
      "nationality": "Non spécifié",
      "description": "Je suis disponible jour et nuit",
      "services": ["Position 69", "Fellation avec préservatif", "Expérience petite amie", "Sexe lesbien", "Massage érotique", "Gorge profonde", "Dirty talk", "Lingerie", "Pour couples"],
      "meetingPlaces": ["Incall", "Outcall"],
      "workingHours": "24/7",
      "gender": "female",
      "location": "Msida",
      "country": "MT",
      "price": 160,
      "height": 159,
      "weight": 54,
      "cupSize": "B"
    },
    {
      "name": "ARIANA",
      "phone": "+35699979724",
      "whatsapp": true,
      "age": 20,
      "nationality": "Non spécifié",
      "description": "Je suis une femme sensuelle, élégante et discrète qui sait comment plaire. Charmante par nature, passionnée par choix - avec moi, tout est question de chimie, de connexion et de moments inoubliables. Laissez-moi être votre plus douce évasion... J'aime vraiment la fête",
      "services": ["Position 69", "Fellation avec préservatif", "Fellation sans préservatif", "Expérience petite amie", "Massage érotique", "Gorge profonde", "Dirty talk"],
      "meetingPlaces": ["Incall", "Outcall"],
      "workingHours": "24/7",
      "gender": "female",
      "location": "Msida",
      "country": "MT",
      "price": 60,
      "height": 160,
      "weight": 50,
      "cupSize": "A"
    },
    {
      "name": "Alexia",
      "phone": "+35699719890",
      "whatsapp": true,
      "age": 32,
      "nationality": "Non spécifié",
      "description": "Nouvelle en ville et très disponible pour tous vos fantasmes avec accent sur être active et passive. Promet un environnement confortable et la plus grande confidentialité.",
      "services": ["Actif/Passif", "BDSM", "Fétichisme"],
      "meetingPlaces": ["Incall"],
      "workingHours": "24/7",
      "gender": "transsexual",
      "location": "Msida",
      "country": "MT",
      "price": 150,
      "height": 175,
      "weight": 60,
      "cupSize": "D"
    },
    {
      "name": "ABBY",
      "phone": "+35699979722",
      "whatsapp": true,
      "age": 19,
      "nationality": "Non spécifié",
      "description": "J'aime faire la fête et passer du bon temps, venez et amusons-nous",
      "services": ["Position 69", "Fellation avec préservatif", "Fellation sans préservatif", "Expérience petite amie", "Massage érotique", "Gorge profonde", "Dirty talk"],
      "meetingPlaces": ["Incall", "Outcall"],
      "workingHours": "24/7",
      "gender": "female",
      "location": "Msida",
      "country": "MT",
      "price": 60,
      "height": 150,
      "weight": 50,
      "cupSize": "A"
    },
    {
      "name": "Jessyka",
      "phone": "+35699672916",
      "whatsapp": true,
      "age": 28,
      "nationality": "Sud-Américaine",
      "description": "La superbe, ensoleillée, chaude, passionnée, douce et sensuelle transsexuelle sud-américaine, à la fois active et passive! Raffinée, polie, élégante et disponible pour diverses demandes. Sexy, captivante et avec un corps incroyable.",
      "services": ["Fellation gorge profonde", "Branlette à deux mains", "Massage corporel à l'huile", "Pénétration dans toutes les positions", "Pluie dorée", "Travestissement", "Éjaculation", "Position 69", "Pour couples", "Rencontres de groupe"],
      "meetingPlaces": ["Incall", "Outcall"],
      "workingHours": "24/7",
      "gender": "transsexual",
      "location": "Msida",
      "country": "MT",
      "price": 150,
      "height": 170,
      "weight": 68,
      "cupSize": "C"
    },
    {
      "name": "NICOLE SANZ",
      "phone": "+35699766757",
      "whatsapp": true,
      "age": 21,
      "nationality": "Non spécifié",
      "description": "Je suis une femme sensuelle, élégante et discrète qui sait comment plaire. Charmante par nature, passionnée par choix - avec moi, tout est question de chimie, de connexion et de moments inoubliables.",
      "services": ["Position 69", "Fellation avec/sans préservatif", "Expérience petite amie", "Massage érotique", "Gorge profonde", "Dirty talk", "Facesitting", "Kamasutra", "Jouets/Godes"],
      "meetingPlaces": ["Incall", "Outcall"],
      "workingHours": "24/7",
      "gender": "female",
      "location": "Msida",
      "country": "MT",
      "price": 60,
      "height": 165,
      "weight": 60,
      "cupSize": "A"
    },
    {
      "name": "Yessica",
      "phone": "+35699532205",
      "whatsapp": true,
      "age": 26,
      "nationality": "Non spécifié",
      "description": "Je suis disponible jour et nuit",
      "services": ["Position 69"],
      "meetingPlaces": ["Incall"],
      "workingHours": "24/7",
      "gender": "female",
      "location": "Msida",
      "country": "MT",
      "price": 50,
      "height": 166,
      "weight": 55,
      "cupSize": "B"
    },
    {
      "name": "Paulina",
      "phone": "+35699705798",
      "whatsapp": true,
      "age": 30,
      "nationality": "Non spécifié",
      "description": "Je suis extravertie, j'aime danser, profiter, j'adore faire la fête, j'ai un cul gourmand et je travaille bien au gymnase.",
      "services": ["Danse", "Massage érotique", "Expérience petite amie"],
      "meetingPlaces": ["Incall", "Outcall"],
      "workingHours": "24/7",
      "gender": "female",
      "location": "Msida",
      "country": "MT",
      "price": 150,
      "height": 168,
      "weight": 55,
      "cupSize": "D"
    },
    {
      "name": "Yara",
      "phone": "+35699196862",
      "whatsapp": true,
      "age": 25,
      "nationality": "Non spécifié",
      "description": "Femme sauvage qui fera exploser vos sens, accommodante au lit, je réalise vos fantasmes, mon visage délicat et ma peau brune vous fascineront",
      "services": ["Position 69", "Fellation sans préservatif", "Expérience petite amie", "Massage érotique", "Massage tantrique", "Massage mousse", "Gorge profonde", "Anulingus", "Fétichisme des pieds", "Douche dorée"],
      "meetingPlaces": ["Incall", "Outcall"],
      "workingHours": "24/7",
      "gender": "female",
      "location": "Msida",
      "country": "MT",
      "price": 120,
      "height": 170,
      "weight": 65,
      "cupSize": "D"
    },
    {
      "name": "Meghan",
      "phone": "+35699970221",
      "whatsapp": true,
      "age": 38,
      "nationality": "Non spécifié",
      "description": "Je suis une femme qui aime vraiment se connecter, à la fois avec l'esprit et avec le cœur. Spirituelle, espiègle et passionnée, j'apprécie les conversations profondes, les rires inattendus et ces moments qui allument l'étincelle.",
      "services": ["Position 69", "Fellation sans préservatif", "Expérience petite amie", "Massage érotique", "Massage de la prostate"],
      "meetingPlaces": ["Incall", "Outcall"],
      "workingHours": "24/7",
      "gender": "female",
      "location": "Msida",
      "country": "MT",
      "price": 100,
      "height": 163,
      "weight": 65,
      "cupSize": "C"
    },
    {
      "name": "Nicol",
      "phone": "+35699034511",
      "whatsapp": true,
      "age": 25,
      "nationality": "Colombienne",
      "description": "Colombienne douce prête à vous satisfaire, j'attends votre message pour que nous vivions une expérience riche et inoubliable",
      "services": ["Sexe lesbien", "Douche dorée", "Jouets/Godes"],
      "meetingPlaces": ["Incall", "Outcall"],
      "workingHours": "24/7",
      "gender": "female",
      "location": "Msida",
      "country": "MT",
      "price": 160,
      "height": 160,
      "weight": 56,
      "cupSize": "B"
    },
    {
      "name": "Andrea",
      "phone": "+35699686786",
      "whatsapp": true,
      "age": 20,
      "nationality": "Latino-Américaine",
      "description": "Je déménage à Malte pour la première fois ici. Je sors et me fais des amis et je suis prête à être coquine! Andrea, 20 ans, d'Amérique latine.",
      "services": ["Position 69", "Fellation avec/sans préservatif", "Expérience petite amie", "Gorge profonde", "Dirty talk", "Fétichisme", "Fétichisme des pieds", "Gode ceinture"],
      "meetingPlaces": ["Incall", "Outcall"],
      "workingHours": "24/7",
      "gender": "female",
      "location": "Msida",
      "country": "MT",
      "price": 120,
      "height": 158,
      "weight": 63,
      "cupSize": "C"
    },
    {
      "name": "Pamela",
      "phone": "+35677234346",
      "whatsapp": true,
      "age": 22,
      "nationality": "Non spécifié",
      "description": "Je suis une fille perverse qui vous rendra toujours heureux et vous voudrez toujours revenir",
      "services": ["Fellation avec préservatif", "Fellation sans préservatif"],
      "meetingPlaces": ["Incall"],
      "workingHours": "24/7",
      "gender": "female",
      "location": "Msida",
      "country": "MT",
      "price": 40,
      "height": 160,
      "weight": 60,
      "cupSize": "B"
    },
    {
      "name": "Alexandra",
      "phone": "+35699160713",
      "whatsapp": true,
      "age": 21,
      "nationality": "Colombienne",
      "description": "Bonjour, bébé, je suis une fille colombienne qui désire vous faire passer un bon moment. Venez avec moi, envoyez-moi un message",
      "services": ["Expérience petite amie", "Massage érotique"],
      "meetingPlaces": ["Incall"],
      "workingHours": "24/7",
      "gender": "female",
      "location": "Msida",
      "country": "MT",
      "price": 100,
      "height": 158,
      "weight": 50,
      "cupSize": "B"
    },
    {
      "name": "Melissa",
      "phone": "+35699330472",
      "whatsapp": true,
      "age": 23,
      "nationality": "Non spécifié",
      "description": "Je suis un volcan chaud, j'aime la fête et passer du bon temps. J'ai un cul avaleur et ma bouche vous attend, je suis votre meilleur chien",
      "services": ["Position 69", "Fellation avec/sans préservatif", "Expérience petite amie", "Massage érotique", "Massage de la prostate", "Massage tantrique", "Gorge profonde", "BDSM", "Bondage", "Services fétichistes", "Jouets/Godes"],
      "meetingPlaces": ["Incall", "Outcall"],
      "workingHours": "24/7",
      "gender": "female",
      "location": "Msida",
      "country": "MT",
      "price": 150,
      "height": 165,
      "weight": 45,
      "cupSize": "D"
    },
    {
      "name": "DOMINATRIX TOP XXL ASHLEY",
      "phone": "+35677248867",
      "whatsapp": true,
      "age": 25,
      "nationality": "Non spécifié",
      "description": "Je suis là maintenant pour vous. Je baise et suce et me fais baiser en anal... Je suis trans avec un beau corps et une grosse bite... Je fais cim et cum sur le visage et le corps",
      "services": ["Sexe anal", "Fellation", "Domination", "BDSM"],
      "meetingPlaces": ["Incall", "Outcall"],
      "workingHours": "24/7",
      "gender": "transsexual",
      "location": "Msida",
      "country": "MT",
      "price": 150,
      "height": 170,
      "weight": 70,
      "cupSize": "A"
    },
    {
      "name": "MELISSA",
      "phone": "+35699330472",
      "whatsapp": true,
      "age": 27,
      "nationality": "Non spécifié",
      "description": "Mon service est complet. Si vous payez pour une heure, j'inclus une fellation sans préservatif. Je fais tout si vous avez une bonne hygiène.",
      "services": ["Position 69", "Sexe anal", "Fellation avec/sans préservatif", "Expérience petite amie", "Services de massage", "BDSM", "Services fétichistes"],
      "meetingPlaces": ["Incall", "Outcall"],
      "workingHours": "24/7",
      "gender": "female",
      "location": "Msida",
      "country": "MT",
      "price": 150,
      "height": 165,
      "weight": 50,
      "cupSize": "C"
    },
    {
      "name": "Luna",
      "phone": "+35699971576",
      "whatsapp": true,
      "age": 27,
      "nationality": "Non spécifié",
      "description": "Bonjour, chéri! Je m'appelle Luna. Je suis belle, délicieuse et sexy, et je vous offre un bonheur charmant et incomparable!",
      "services": ["Fellation avec/sans préservatif", "Expérience petite amie", "Services lesbiens", "Massage érotique", "Massage tantrique", "Massage de la prostate", "Massage mousse", "Massage anal", "Bondage", "Services fétichistes", "Fessée", "Gode ceinture"],
      "meetingPlaces": ["Incall", "Outcall"],
      "workingHours": "24/7",
      "gender": "female",
      "location": "Msida",
      "country": "MT",
      "price": 130,
      "height": 165,
      "weight": 65,
      "cupSize": "B"
    },
    {
      "name": "María José",
      "phone": "+35699160713",
      "whatsapp": true,
      "age": 22,
      "nationality": "Colombienne",
      "description": "Bonjour, bébé, je suis une fille colombienne qui désire vous faire passer un bon moment.",
      "services": ["Expérience petite amie", "Massage érotique"],
      "meetingPlaces": ["Incall", "Outcall"],
      "workingHours": "24/7",
      "gender": "female",
      "location": "Msida",
      "country": "MT",
      "price": 160,
      "height": 158,
      "weight": 50,
      "cupSize": "A"
    },
    {
      "name": "Ash Lopez",
      "phone": "+35677289474",
      "whatsapp": true,
      "age": 28,
      "nationality": "Non spécifié",
      "description": "Une transsexuelle brune offrant des services d'escorte de luxe. Déclare 'Je vous reçois exactement comme je me vois sur la photo' et met l'accent sur les préférences de propreté.",
      "services": ["Position 69", "Sexe anal", "Fellation avec/sans préservatif", "Expérience petite amie", "Massage érotique", "Massage de la prostate", "Gorge profonde", "Fisting", "BDSM", "Fétichisme", "Douche dorée", "Fessée"],
      "meetingPlaces": ["Incall", "Outcall"],
      "workingHours": "24/7",
      "gender": "transsexual",
      "location": "Msida",
      "country": "MT",
      "price": 150,
      "height": 170,
      "weight": 78,
      "cupSize": "F"
    },
    {
      "name": "Alison",
      "phone": "+35699437996",
      "whatsapp": true,
      "age": 25,
      "nationality": "Non spécifié",
      "description": "Bonjour, je suis une nouvelle fille sur l'île, je suis amusante et chaude. Venez avoir le plaisir de vous servir et de vous faire passer un moment incroyable avec moi",
      "services": ["Expérience petite amie", "Massage érotique"],
      "meetingPlaces": ["Outcall"],
      "workingHours": "24/7",
      "gender": "female",
      "location": "Msida",
      "country": "MT",
      "price": 200,
      "height": 165,
      "weight": 65,
      "cupSize": "B"
    },
    {
      "name": "Joselyn",
      "phone": "+35677206496",
      "whatsapp": true,
      "age": 24,
      "nationality": "Non spécifié",
      "description": "Polie, aimante, affectueuse, un peu rude, je suis forte, j'aime les cadeaux, j'aime m'amuser. J'aime tout. Je profite de la vie, sexuellement une héroïne.",
      "services": ["Position 69", "Sexe anal", "Fellation avec/sans préservatif", "Expérience petite amie", "Léchage et succion de boules", "Facesitting", "Fisting", "Rasage intime", "Massage de la prostate", "Douche dorée"],
      "meetingPlaces": ["Incall"],
      "workingHours": "24/7",
      "gender": "transsexual",
      "location": "Msida",
      "country": "MT",
      "price": 150,
      "height": 175,
      "weight": 69,
      "cupSize": "A"
    },
    {
      "name": "Laura",
      "phone": "+35677579542",
      "whatsapp": true,
      "age": 41,
      "nationality": "Non spécifié",
      "description": "De retour à Malte, prête et disposée à performer pour votre divertissement. Je suis une dame extravertie avec une personnalité intéressante et une soif insatiable de sexe",
      "services": ["Expérience petite amie", "Accompagnement"],
      "meetingPlaces": ["Incall"],
      "workingHours": "24/7",
      "gender": "female",
      "location": "Msida",
      "country": "MT",
      "price": 150,
      "height": 165,
      "weight": 77,
      "cupSize": "D"
    },
    {
      "name": "Anahí",
      "phone": "+35699766757",
      "whatsapp": true,
      "age": 25,
      "nationality": "Non spécifié",
      "description": "Je suis une blonde très accommodante, venez amusons-nous. Blonde sauvage avec des tatouages qui aime explorer les fantasmes et repousser les limites.",
      "services": ["Position 69", "Fellation avec préservatif", "Fellation sans préservatif", "Expérience petite amie", "Massage érotique", "Gorge profonde", "Dirty talk"],
      "meetingPlaces": ["Incall"],
      "workingHours": "24/7",
      "gender": "female",
      "location": "Msida",
      "country": "MT",
      "price": 50,
      "height": 156,
      "weight": 50,
      "cupSize": "C"
    },
    {
      "name": "Rafaella",
      "phone": "+35677228919",
      "whatsapp": true,
      "age": 25,
      "nationality": "Brésilienne",
      "description": "Je suis une fille brésilienne très sensuelle et attirante, je suis ici pour vous satisfaire autant que possible et vous offrir de nombreux moments de plaisir.",
      "services": ["Position 69", "Sexe anal", "Fellation avec/sans préservatif", "Expérience petite amie", "Massage érotique", "Massage de la prostate", "Massage anal", "Gorge profonde", "Dirty talk", "Kamasutra", "Lingerie", "Expérience pornstar", "Anulingus", "Jouets/Godes", "Couples", "BDSM", "Sexe clinique", "Fétichisme", "Douche dorée", "Gode ceinture"],
      "meetingPlaces": ["Incall", "Outcall"],
      "workingHours": "07:00 - 00:00",
      "gender": "female",
      "location": "Msida",
      "country": "MT",
      "price": 150,
      "height": 170,
      "weight": 63,
      "cupSize": "C"
    },
    {
      "name": "Lili",
      "phone": "+35699086005",
      "whatsapp": true,
      "age": 20,
      "nationality": "Non spécifié",
      "description": "Belle fille prête à être votre fantasme qui se décrit comme très amusante, jolie et chaude. Elle met l'accent sur la disponibilité et la réactivité aux messages.",
      "services": ["Fellation avec/sans préservatif", "Expérience petite amie", "Massage érotique", "Massage de la prostate", "Massage tantrique", "Bondage", "Sexe clinique", "Services fétichistes", "Fétichisme des pieds", "Cuir/Latex/PVC", "Fessée"],
      "meetingPlaces": ["Incall", "Outcall"],
      "workingHours": "24/7",
      "gender": "female",
      "location": "Msida",
      "country": "MT",
      "price": 50,
      "height": 163,
      "weight": 50,
      "cupSize": "A"
    },
    {
      "name": "Paulina",
      "phone": "+35699647699",
      "whatsapp": true,
      "age": 19,
      "nationality": "Non spécifié",
      "description": "Je réaliserai vos souhaits",
      "services": ["Expérience petite amie"],
      "meetingPlaces": ["Incall", "Outcall"],
      "workingHours": "24/7",
      "gender": "female",
      "location": "Msida",
      "country": "MT",
      "price": 160,
      "height": 155,
      "weight": 53,
      "cupSize": "A"
    },
    {
      "name": "KATHERIN NEW",
      "phone": "+35699741303",
      "whatsapp": true,
      "age": 26,
      "nationality": "Vénézuélienne",
      "description": "Belle Trans, Katherine nouveau top model, je suis une jeune princesse vénézuélienne, super féminine, magnifique et très sexy. Corps incroyable, avec des courbes.",
      "services": ["Position 69", "Sexe anal", "Fellation avec préservatif", "Expérience petite amie", "Massage érotique", "Massage de la prostate", "Massage anal", "Léchage et succion de boules", "Dirty talk", "Fisting", "Anulingus", "Jouets/Godes", "Pour couples", "BDSM", "Fétichisme", "Fétichisme des pieds", "Cuir/Latex/PVC", "Maîtresse", "Fessée", "Gode ceinture", "Squirting"],
      "meetingPlaces": ["Incall", "Outcall"],
      "workingHours": "24/7",
      "gender": "transsexual",
      "location": "Msida",
      "country": "MT",
      "price": 150,
      "height": 170,
      "weight": 67,
      "cupSize": "D"
    },
    {
      "name": "Viky",
      "phone": "+35699589456",
      "whatsapp": true,
      "age": 22,
      "nationality": "Colombienne",
      "description": "Bonjour amour, je suis une fille colombienne avec un désir de vous faire passer un bon moment, venez avec moi, envoyez-moi un massage",
      "services": ["Fellation avec préservatif", "Lingerie", "Fétichisme des pieds", "Douche dorée"],
      "meetingPlaces": ["Outcall"],
      "workingHours": "24/7",
      "gender": "female",
      "location": "Msida",
      "country": "MT",
      "price": 200,
      "height": 152,
      "weight": 49,
      "cupSize": "A"
    },
    {
      "name": "MiA",
      "phone": "+35699976128",
      "whatsapp": true,
      "age": 25,
      "nationality": "Argentine",
      "description": "Je suis une Argentine sexy avec un service promotionnel",
      "services": ["Expérience petite amie", "Massage érotique"],
      "meetingPlaces": ["Incall", "Outcall"],
      "workingHours": "24/7",
      "gender": "female",
      "location": "Msida",
      "country": "MT",
      "price": 150,
      "height": 160,
      "weight": 45,
      "cupSize": "C"
    },
    {
      "name": "Armira",
      "phone": "+35677215793",
      "whatsapp": true,
      "age": 27,
      "nationality": "Non spécifié",
      "description": "Bonjour, je m'appelle Armira, j'ai 27 ans, je suis une personne très gentille et j'aimerais donner à mes clients un bon moment",
      "services": ["Expérience petite amie", "Massage érotique"],
      "meetingPlaces": ["Incall", "Outcall"],
      "workingHours": "24/7",
      "gender": "female",
      "location": "Msida",
      "country": "MT",
      "price": 100,
      "height": 160,
      "weight": 52,
      "cupSize": "A"
    }
  ]
}
